qface_qtqml-1.2.dist-info/DESCRIPTION.rst
qface_qtqml-1.2.dist-info/METADATA
qface_qtqml-1.2.dist-info/RECORD
qface_qtqml-1.2.dist-info/WHEEL
qface_qtqml-1.2.dist-info/entry_points.txt
qface_qtqml-1.2.dist-info/metadata.json
qface_qtqml-1.2.dist-info/top_level.txt
qtqml/__about__.py
qtqml/__init__.py
qtqml/qtqml.py
qtqml/templates/Interface.qml
qtqml/templates/__init__.py
qtqml/templates/copyright.h
qtqml/templates/qmldir
qtqml/templates/private/AbstractInterface.qml
qtqml/templates/private/__init__.py
qtqml/templates/private/module.js
qtqml/templates/private/qmldir
